mytestis/__init__.py
mytestis/main.py
mytestis/.system/imports.py
mytestis/.system/index.py
mytestis/.system/modules/jobs.py
mytestis/.system/sources/-clight.json
mytestis/.system/sources/clight.json
mytestis/.system/sources/logo.ico
mytestis-0.0.6.dist-info/LICENSE
mytestis-0.0.6.dist-info/METADATA
mytestis-0.0.6.dist-info/WHEEL
mytestis-0.0.6.dist-info/entry_points.txt
mytestis-0.0.6.dist-info/top_level.txt
mytestis-0.0.6.dist-info/RECORD
